MANIFEST.in
README.md
README.zh-CN.md
requirements.txt
setup.py
demo/__init__.py
demo/generate_following.py
keras_gpt_2/__init__.py
keras_gpt_2/bpe.py
keras_gpt_2/gen.py
keras_gpt_2/loader.py
keras_gpt_2/model.py
keras_gpt_2.egg-info/PKG-INFO
keras_gpt_2.egg-info/SOURCES.txt
keras_gpt_2.egg-info/dependency_links.txt
keras_gpt_2.egg-info/requires.txt
keras_gpt_2.egg-info/top_level.txt
tests/__init__.py
tests/test_bpe.py
tests/test_gen.py
tests/test_loader.py
tests/test_model.py