Metadata-Version: 2.1
Name: keras-gpt-2
Version: 0.17.0
Summary: GPT-2
Home-page: https://github.com/CyberZHG/keras-gpt-2
Author: CyberZHG
Author-email: CyberZHG@users.noreply.github.com
License: MIT
Platform: UNKNOWN
Classifier: Programming Language :: Python :: 3
Classifier: License :: OSI Approved :: MIT License
Classifier: Operating System :: OS Independent
